ibdata_pymerkle/__init__.py
ibdata_pymerkle/cli.py
ibdata_pymerkle/config.py
ibdata_pymerkle/hash_utils.py
ibdata_pymerkle/ibdata_constants.py
ibdata_pymerkle/merkle_tree.py
ibdata_pymerkle/package.py
ibdata_pymerkle-0.1.0.dist-info/METADATA
ibdata_pymerkle-0.1.0.dist-info/WHEEL
ibdata_pymerkle-0.1.0.dist-info/entry_points.txt
ibdata_pymerkle-0.1.0.dist-info/licenses/LICENSE
ibdata_pymerkle-0.1.0.dist-info/RECORD
