Metadata-Version: 2.4
Name: ibdata-pymerkle
Version: 0.1.0
Summary: Configurable SHA merkle tree generator for directory structures
Project-URL: Homepage, https://github.com/infrastructurebuilder/ibdata-pymerkle
Project-URL: Repository, https://github.com/infrastructurebuilder/ibdata-pymerkle
Project-URL: Issues, https://github.com/infrastructurebuilder/ibdata-pymerkle/issues
Author-email: Mykel Alvis <mykel.alvis@gmail.com>
License: Apache-2.0
License-File: LICENSE
Classifier: Development Status :: 4 - Beta
Classifier: Intended Audience :: Developers
Classifier: Intended Audience :: Science/Research
Classifier: License :: OSI Approved :: Apache Software License
Classifier: Programming Language :: Python :: 3
Classifier: Programming Language :: Python :: 3.9
Classifier: Programming Language :: Python :: 3.10
Classifier: Programming Language :: Python :: 3.11
Classifier: Programming Language :: Python :: 3.12
Classifier: Topic :: Software Development :: Code Generators
Requires-Python: >=3.9
